easy_atom/__init__.py
easy_atom/action.py
easy_atom/atom.py
easy_atom/content.py
easy_atom/helpers.py
atom_gen-1.1.dist-info/LICENSE.txt
atom_gen-1.1.dist-info/METADATA
atom_gen-1.1.dist-info/WHEEL
atom_gen-1.1.dist-info/top_level.txt
atom_gen-1.1.dist-info/RECORD
